{
    "AX": {
        "error": 0.009591505657171198,
        "error_type": "SEM",
        "filter_outliers_dict": {
            "filter_outliers": true,
            "iterations": 1,
            "std_devs": 3,
            "use_iqr_filtering": false,
            "use_standard_deviation_filtering": false
        },
        "fit": "average",
        "fn": 30,
        "include_baseline_error": false,
        "n": 30,
        "outlier_excluded": [],
        "reviewed": true,
        "user_excluded": [],
        "value": -0.20909310380617777
    },
    "CDD": {
        "error": 3.5971600556303037e-05,
        "error_type": "SEM",
        "filter_outliers_dict": {
            "filter_outliers": true,
            "iterations": 1,
            "std_devs": 10,
            "use_iqr_filtering": false,
            "use_standard_deviation_filtering": false
        },
        "fit": "average",
        "fn": 30,
        "include_baseline_error": false,
        "n": 30,
        "outlier_excluded": [],
        "reviewed": true,
        "user_excluded": [],
        "value": 0.0003511346032610163
    },
    "H1": {
        "error": 0.008826195589232635,
        "error_type": "SEM",
        "filter_outliers_dict": {
            "filter_outliers": true,
            "iterations": 1,
            "std_devs": 3,
            "use_iqr_filtering": false,
            "use_standard_deviation_filtering": false
        },
        "fit": "average",
        "fn": 30,
        "include_baseline_error": false,
        "n": 30,
        "outlier_excluded": [],
        "reviewed": true,
        "user_excluded": [],
        "value": 0.05337057604144017
    },
    "H2": {
        "error": 0.005236288400166706,
        "error_type": "SEM",
        "filter_outliers_dict": {
            "filter_outliers": true,
            "iterations": 1,
            "std_devs": 3,
            "use_iqr_filtering": false,
            "use_standard_deviation_filtering": false
        },
        "fit": "average",
        "fn": 30,
        "include_baseline_error": false,
        "n": 30,
        "outlier_excluded": [],
        "reviewed": true,
        "user_excluded": [],
        "value": 0.013335114306149384
    },
    "L1": {
        "error": 0.003789768097050598,
        "error_type": "SEM",
        "filter_outliers_dict": {
            "filter_outliers": true,
            "iterations": 1,
            "std_devs": 3,
            "use_iqr_filtering": false,
            "use_standard_deviation_filtering": false
        },
        "fit": "average",
        "fn": 30,
        "include_baseline_error": false,
        "n": 30,
        "outlier_excluded": [],
        "reviewed": true,
        "user_excluded": [],
        "value": 0.010280558749946067
    },
    "L2": {
        "error": 0.003316307741863253,
        "error_type": "SEM",
        "filter_outliers_dict": {
            "filter_outliers": true,
            "iterations": 1,
            "std_devs": 2
        },
        "fit": "average",
        "value": -0.005267155910290072
    }
}