{
    "Ar36": {
        "error": 0.0017316822156093544,
        "error_type": "SEM",
        "filter_outliers_dict": {
            "filter_outliers": true,
            "iterations": 1,
            "std_devs": 3,
            "use_iqr_filtering": false,
            "use_standard_deviation_filtering": false
        },
        "fit": "linear",
        "fn": 120,
        "include_baseline_error": true,
        "n": 120,
        "outlier_excluded": [],
        "reviewed": true,
        "user_excluded": [],
        "value": 0.5772019397214425
    },
    "Ar37": {
        "error": 0.008291773424178939,
        "error_type": "SEM",
        "filter_outliers_dict": {
            "filter_outliers": true,
            "iterations": 1,
            "std_devs": 3,
            "use_iqr_filtering": false,
            "use_standard_deviation_filtering": false
        },
        "fit": "linear",
        "fn": 118,
        "include_baseline_error": true,
        "n": 120,
        "outlier_excluded": [
            0,
            1
        ],
        "reviewed": true,
        "user_excluded": [],
        "value": 7.196633054980693
    },
    "Ar38": {
        "error": 0.006083446103440867,
        "error_type": "SEM",
        "filter_outliers_dict": {
            "filter_outliers": true,
            "iterations": 1,
            "std_devs": 3,
            "use_iqr_filtering": false,
            "use_standard_deviation_filtering": false
        },
        "fit": "linear",
        "fn": 118,
        "include_baseline_error": true,
        "n": 120,
        "outlier_excluded": [
            0,
            1
        ],
        "reviewed": true,
        "user_excluded": [],
        "value": 0.28109536927197354
    },
    "Ar39": {
        "error": 0.013893375225449167,
        "error_type": "SEM",
        "filter_outliers_dict": {
            "filter_outliers": true,
            "iterations": 1,
            "std_devs": 3,
            "use_iqr_filtering": false,
            "use_standard_deviation_filtering": false
        },
        "fit": "linear",
        "fn": 119,
        "include_baseline_error": true,
        "n": 120,
        "outlier_excluded": [
            0
        ],
        "reviewed": true,
        "user_excluded": [],
        "value": 10.462193638655151
    },
    "Ar40": {
        "error": 0.025355737525268523,
        "error_type": "SEM",
        "filter_outliers_dict": {
            "filter_outliers": true,
            "iterations": 1,
            "std_devs": 3,
            "use_iqr_filtering": false,
            "use_standard_deviation_filtering": false
        },
        "fit": "linear",
        "fn": 119,
        "include_baseline_error": true,
        "n": 120,
        "outlier_excluded": [
            49
        ],
        "reviewed": true,
        "user_excluded": [],
        "value": 210.18168728299645
    },
    "Ar41": {
        "error": 0.0031584992188933435,
        "error_type": "SEM",
        "filter_outliers_dict": {
            "filter_outliers": true,
            "iterations": 1,
            "std_devs": 2
        },
        "fit": "Average",
        "value": 0.07637912864270732
    }
}